mldatakit/__init__.py
mldatakit-0.1.dist-info/METADATA
mldatakit-0.1.dist-info/RECORD
mldatakit-0.1.dist-info/WHEEL
mldatakit-0.1.dist-info/top_level.txt
