Metadata-Version: 2.1
Name: mldatakit
Version: 0.1
Summary: Data conversion and download utility for Machine Learning.
Home-page: https://github.com/ml-data-kit/ml-data-kit
Author: UNKNOWN
Author-email: UNKNOWN
License: Apache
Keywords: Machine Learning,Data,Data Conversion,Data Processing
Platform: UNKNOWN
Classifier: Intended Audience :: Developers
Classifier: Intended Audience :: Science/Research
Classifier: Natural Language :: English
Classifier: Programming Language :: Python
